ps_log/__init__.py
ps_log/log_service.py
ps_common-1.0.0.0.dist-info/METADATA
ps_common-1.0.0.0.dist-info/WHEEL
ps_common-1.0.0.0.dist-info/top_level.txt
ps_common-1.0.0.0.dist-info/RECORD
