Metadata-Version: 2.1
Name: ps-common
Version: 1.0.0.0
Author: maoyawei
Requires-Dist: loguru
